winternlc/__init__.py
winternlc/apply.py
winternlc/config.py
winternlc/get_corrections.py
winternlc/mask.py
winternlc/non_linear_correction.py
winternlc/rational.py
winternlc/versions.py
winternlc/zenodo.py
winternlc/create/__init__.py
winternlc/create/make_generic_rational_corrections.py
winternlc/create/make_linearpoly_corrections.py
winternlc/create/make_linpoly_corrections_multi.py
winternlc/create/make_linpoly_corrections_multi_split.py
winternlc/create/make_median_img.py
winternlc/create/make_polynomial_corrections.py
winternlc/create/make_rationial8_multithread_corrections.py
winternlc/create/split_linpoly_corrections.py
winternlc/create/update_test_images_latest_version.py
winternlc/create/utils.py
winternlc-2.1.0.dist-info/licenses/LICENSE
winternlc-2.1.0.dist-info/METADATA
winternlc-2.1.0.dist-info/WHEEL
winternlc-2.1.0.dist-info/entry_points.txt
winternlc-2.1.0.dist-info/top_level.txt
winternlc-2.1.0.dist-info/RECORD
