Metadata-Version: 2.4
Name: winternlc
Version: 2.1.0
Author-email: Danielle Frostig <frostig@mit.edu>, Robert Stein <rdstein@caltech.edu>
License: MIT
Project-URL: Homepage, https://github.com/winter-telescope/winternlc
Classifier: Programming Language :: Python :: 3
Classifier: Programming Language :: Python :: 3.10
Classifier: Programming Language :: Python :: 3.11
Classifier: Programming Language :: Python :: 3.12
Classifier: Programming Language :: Python :: 3.13
Classifier: Intended Audience :: Science/Research
Classifier: Intended Audience :: End Users/Desktop
Classifier: Intended Audience :: Developers
Classifier: Natural Language :: English
Classifier: Topic :: Scientific/Engineering
Classifier: Topic :: Scientific/Engineering :: Astronomy
Classifier: Topic :: Scientific/Engineering :: Physics
Classifier: Operating System :: POSIX
Classifier: Operating System :: Unix
Classifier: Operating System :: MacOS
Requires-Python: >=3.10
License-File: LICENSE
Requires-Dist: numpy
Requires-Dist: matplotlib
Requires-Dist: astropy
Requires-Dist: scipy
Requires-Dist: pre-commit
Provides-Extra: dev
Requires-Dist: black==24.4.2; extra == "dev"
Requires-Dist: isort==5.13.2; extra == "dev"
Requires-Dist: pylint==3.2.2; extra == "dev"
Requires-Dist: coveralls; extra == "dev"
Dynamic: license-file
